ajoycon/__init__.py
ajoycon/async_events.py
ajoycon/async_gyro.py
ajoycon/async_joycon.py
ajoycon/constants.py
ajoycon/discovery.py
ajoycon/models.py
ajoycon-1.0.1.dist-info/METADATA
ajoycon-1.0.1.dist-info/WHEEL
ajoycon-1.0.1.dist-info/licenses/LICENSE
ajoycon-1.0.1.dist-info/RECORD
