Metadata-Version: 2.4
Name: ajoycon
Version: 1.0.1
Summary: Modern async Python driver for Nintendo Switch Joy-Con
Project-URL: Homepage, https://github.com/Technoculture/ajoycon
Project-URL: Repository, https://github.com/Technoculture/ajoycon
Author: Technoculture Research
License: MIT
License-File: LICENSE
Keywords: bluetooth,controller,joycon,nintendo,switch
Requires-Python: >=3.13
Requires-Dist: hidapi>=0.14.0
Requires-Dist: pyglm>=2.7.0
Provides-Extra: dev
Requires-Dist: pytest>=7.0.0; extra == 'dev'
Requires-Dist: ruff>=0.1.0; extra == 'dev'
